MANIFEST.in
requirements.txt
setup.py
cloudtts/__init__.py
cloudtts/aws.py
cloudtts/client.py
cloudtts/google.py
cloudtts/ibm.py
cloudtts/microsoft.py
cloudtts.egg-info/PKG-INFO
cloudtts.egg-info/SOURCES.txt
cloudtts.egg-info/dependency_links.txt
cloudtts.egg-info/requires.txt
cloudtts.egg-info/top_level.txt