Metadata-Version: 1.1
Name: cloudtts
Version: 0.0.2
Summary: Wrapper Library for Text to Speech API services
Home-page: https://github.com/bengo4/cloudtts
Author: Mitsuhiro Setoguchi
Author-email: setoguchi@bengo4.com
License: MIT
Platform: any
Classifier: Programming Language :: Python :: 3
Classifier: License :: OSI Approved :: MIT License
Classifier: Operating System :: OS Independent
